LICENSE
MANIFEST.in
README.md
setup.cfg
setup.py
stnm/__init__.py
stnm/config.py
stnm/constants.py
stnm/install.py
stnm/response.py
stnm/run.py
stnm/shell.py
stnm/start.py
stnm/status.py
stnm/stop.py
stnm.egg-info/PKG-INFO
stnm.egg-info/SOURCES.txt
stnm.egg-info/dependency_links.txt
stnm.egg-info/entry_points.txt
stnm.egg-info/requires.txt
stnm.egg-info/top_level.txt
stnm/test/__init__.py
stnm/test/config_test.py
stnm/web/__init__.py
stnm/web/app.py
stnm/web/static/vendor/babel.min.js
stnm/web/static/vendor/bootstrap.bundle.min.js
stnm/web/static/vendor/bootstrap.min.css
stnm/web/static/vendor/jquery.min.js
stnm/web/static/vendor/react-bootstrap.min.js
stnm/web/static/vendor/react-dom.production.min.js
stnm/web/static/vendor/react-router-dom.min.js
stnm/web/static/vendor/react.production.min.js
stnm/web/static/vendor/toastr.min.css
stnm/web/static/vendor/toastr.min.js
stnm/web/templates/index.jinja2
stnm/web/templates/jsx/config-editor.jsx
stnm/web/templates/jsx/config-info.jsx
stnm/web/templates/jsx/config-provider.jsx
stnm/web/templates/jsx/mining.jsx
stnm/web/templates/jsx/node-info.jsx
stnm/web/templates/jsx/node-provider.jsx
stnm/web/templates/jsx/panel.jsx