Metadata-Version: 1.0
Name: stnm
Version: 0.3.1
Summary: Stacks blockchain node process manager
Home-page: https://github.com/talhasch/stnm
Author: Talha Buğra Bulut
Author-email: talhabugrabulut@gmail.com
License: UNKNOWN
Platform: UNKNOWN
